pygenec/__init__.py
pygenec/algoritmogenetico.py
pygenec/evolucao.py
pygenec/populacao.py
pygenec/tools.py
pygenec/cruzamento/__init__.py
pygenec/cruzamento/cruzamento.py
pygenec/cruzamento/embaralhamento.py
pygenec/cruzamento/fatias.py
pygenec/cruzamento/kpontos.py
pygenec/cruzamento/umponto.py
pygenec/mutacao/__init__.py
pygenec/mutacao/duplatroca.py
pygenec/mutacao/flip.py
pygenec/mutacao/mutacao.py
pygenec/mutacao/ntrocas.py
pygenec/mutacao/sequenciareversa.py
pygenec/selecao/__init__.py
pygenec/selecao/classificacao.py
pygenec/selecao/roleta.py
pygenec/selecao/selecao.py
pygenec/selecao/torneio.py
pygenec-1.1.1.dist-info/LICENSE
pygenec-1.1.1.dist-info/METADATA
pygenec-1.1.1.dist-info/WHEEL
pygenec-1.1.1.dist-info/top_level.txt
pygenec-1.1.1.dist-info/RECORD
