Metadata-Version: 2.1
Name: pygenec
Version: 1.1.1
Summary: Algoritmo Genetico em Python e Numpy
Home-page: https://github.com/duducosmos/pygenec
Author: Eduardo S. Pereira
Author-email: pereira.somoza@gmail.com
License: Apache License 2.0
Platform: UNKNOWN
Requires-Dist: numpy
Requires-Dist: pathos
